tom_fink/__init__.py
tom_fink/alertstream.py
tom_fink/fink.py
tom_fink/tests/__init__.py
tom_fink/tests/boot_django.py
tom_fink/tests/django_shell.py
tom_fink/tests/run_canary_tests.py
tom_fink/tests/run_tests.py
tom_fink/tests/tests.py
tom_fink/tests/tests_canary.py
tom_fink-0.7.6.dist-info/LICENSE
tom_fink-0.7.6.dist-info/METADATA
tom_fink-0.7.6.dist-info/WHEEL
tom_fink-0.7.6.dist-info/RECORD
