Metadata-Version: 2.3
Name: tom-fink
Version: 0.7.6
Summary: The Fink Alert Broker Module for the TOM Toolkit. Fink is a broker currently connected to ZTF. More information on Fink at https://fink-portal.org
License: GPL-3.0 license
Keywords: tomtoolkit,astronomy,astrophysics,cosmology,science,observatory,alert,broker,fink
Author: Julien Peloton
Author-email: peloton@lal.in2p3.fr
Maintainer: William Lindstrom
Maintainer-email: llindstrom@lco.global
Requires-Python: >=3.9,<3.13
Classifier: Development Status :: 3 - Alpha
Classifier: Intended Audience :: Science/Research
Classifier: License :: OSI Approved :: BSD License
Classifier: Operating System :: OS Independent
Classifier: Programming Language :: Python :: 3
Classifier: Programming Language :: Python :: 3.11
Classifier: Topic :: Scientific/Engineering :: Astronomy
Classifier: Topic :: Scientific/Engineering :: Physics
Requires-Dist: Markdown (>=3.5.2,<4)
Requires-Dist: elasticsearch-dsl (>=8.12.0,<9)
Requires-Dist: fink-client (>=8.8,<9)
Requires-Dist: tom-alertstreams (>=0.6.2,<2.0)
Requires-Dist: tomtoolkit (>=2.17.2,<3)
